{"indicator_id":518,"guid":"PUDH:INDI:SaE05b","is_cuantitative":false,"dataset_id":"PUDH:INDI:","institution_code":"PUDH","research_code":"INDI","right_name":"Derecho a la Salud","right_key":"S","right_name_short":"Salud","category_id":1,"indicator_category_name":"Recepción del derecho","indicator_category_key":"a","indicator_type":"Estructural","indicator_type_short":"Estructural","indicator_type_code":"E","indicator_code":"SaE05b","indicator_sequence":"020102105b","indicator_name":"Ratificación de Tratados Internacionales que reconocen el Derecho a la Salud (v)","indicator_definition":"México ratificó el Convenio Internacional del Trabajo No. 155 sobre Seguridad y Salud de los Trabajadores y Medio Ambiente de Trabajo.","right_id":2,"indicator_type_id":1,"indicator_category_id":1,"indicator_formule_code":null,"indicator_calculation_element":null,"indicator_source_formule":null,"indicator_measure_unit":null,"indicator_justification":null,"indicator_reference":null,"indicator_observation":null,"indicator_comments":null,"responsible_institution":null,"lastmodified":"2019-11-05 00:00:00.0","modified":"2019-11-05 00:00:00.0","type_collection":"Derechos Humanos","collection_type":"Derechos Humanos","parent_cat_noun":"Indicadores, Programa Universitario de Derechos Humanos","title":"Ratificación de Tratados Internacionales que reconocen el Derecho a la Salud (v)","label":"Ratificación de Tratados Internacionales que reconocen el Derecho a la Salud (v)","data_category":"Registros","data_source":"indicator","data_descr":"Indicador","parent_category":"Acervos","evidence":[{"evidence_id":649,"evidence_name":"Convenio Internacional del Trabajo No. 155 sobre Seguridad y Salud de los Trabajadores y Medio Ambiente de Trabajo","evidence_url":"https:\/\/aplicaciones.sre.gob.mx\/tratados\/muestratratado_nva.sre?id_tratado=409&depositario=0","indicator_id":518,"update_date":"2019-05-27","supplementary_documents":null,"supplementary_documents_url":null,"evidence_observations":null,"institution_evidence_id":66,"institution_name_evidencie":"Secretaría de Relaciones Exteriores","institution_code_evidencie":"SRE","institution_headboard":"0","validity_year_start":0,"validity_end_start":0,"observation_unit_id":4,"observation_unit_name":"Convenio","observation_unit_description":"Convenio","observation_unit_priorit":1,"paper":[{"paper_id":507,"evidence_id":649,"paper_sequence":"4","paper_name":"1. Todo Miembro deberá, en consulta con las organizaciones más representativas de empleadores y trabajadores interesadas y habida cuenta de las condiciones y práctica nacionales, formular, poner en práctica y reexaminar periódicamente una política nacional coherente en materia de seguridad y salud de los trabajadores y medio ambiente de trabajo.\r\n2. Esta política tendrá por objeto prevenir los accidentes y los daños para la salud que sean consecuencia del trabajo, guarden relación con la actividad laboral o sobrevengan durante el trabajo, reduciendo al mínimo, en la medida en que sea razonable y factible, las causas de los riesgos inherentes al medio ambiente de trabajo."}],"validity_date_evidence":[{"validity_date_id":659,"evidence_id":649,"validity_date":"1981-06-22","date_type_name":"Firma"},{"validity_date_id":660,"evidence_id":649,"validity_date":"1981-06-22","date_type_name":"Adhesión"},{"validity_date_id":661,"evidence_id":649,"validity_date":"1983-10-28","date_type_name":"Aceptación"},{"validity_date_id":662,"evidence_id":649,"validity_date":"1983-12-01","date_type_name":"Publicación"},{"validity_date_id":663,"evidence_id":649,"validity_date":"1984-02-01","date_type_name":"Vinculación"},{"validity_date_id":664,"evidence_id":649,"validity_date":"1985-02-01","date_type_name":"Entrada en vigor"}]}],"identifier":"PUDH:INDI:SaE05b"}